esdateutil/__init__.py
esdateutil/dateformat.py
esdateutil/datemath.py
esdateutil-1.0.1.dist-info/LICENSE
esdateutil-1.0.1.dist-info/METADATA
esdateutil-1.0.1.dist-info/WHEEL
esdateutil-1.0.1.dist-info/top_level.txt
esdateutil-1.0.1.dist-info/RECORD
