Metadata-Version: 2.1
Name: esdateutil
Version: 1.0.1
Summary: Elasticsearch datemath and dateformat parsing library. Zero dependencies
Author-email: Matthew Murr <matt@murr.dev>
License: Copyright (c) 2024 Matthew Murr
Project-URL: Homepage, https://git.sr.ht/~murr/esdateutil
Project-URL: Repository, https://git.sr.ht/~murr/esdateutil
Project-URL: Documentation, https://git.sr.ht/~murr/esdateutil/tree/master/item/README.md
Keywords: elasticsearch,elastic,es,datemath,parser,date,format
Classifier: Development Status :: 5 - Production/Stable
Classifier: Intended Audience :: Developers
Classifier: Programming Language :: Python :: 3
Classifier: License :: OSI Approved :: MIT License
Classifier: Operating System :: OS Independent
Classifier: Topic :: Software Development :: Libraries
Requires-Python: >=3.3
License-File: LICENSE
